ipynb_renderer/__init__.py
ipynb_renderer/custom_exception.py
ipynb_renderer/logger.py
ipynb_renderer/site.py
ipynb_renderer/youtube.py
ipynb_renderer_ucn-0.2.1.dist-info/LICENSE
ipynb_renderer_ucn-0.2.1.dist-info/METADATA
ipynb_renderer_ucn-0.2.1.dist-info/WHEEL
ipynb_renderer_ucn-0.2.1.dist-info/top_level.txt
ipynb_renderer_ucn-0.2.1.dist-info/RECORD
